sbx_whisper_import/__init__.py
sbx_whisper_import/cli.py
sbx_whisper_import/hf_whisper_importer.py
sbx_whisper_import/metadata.yaml
sbx_whisper_import/py.typed
sbx_whisper_import/whisper_import.py
sparv_sbx_whisper_import-0.2.0.dist-info/WHEEL
sparv_sbx_whisper_import-0.2.0.dist-info/entry_points.txt
sparv_sbx_whisper_import-0.2.0.dist-info/METADATA
sparv_sbx_whisper_import-0.2.0.dist-info/RECORD
