Metadata-Version: 2.3
Name: sparv-sbx-whisper-import
Version: 0.2.0
Summary: Allow Sparv to import audio as text with KB Whisper
Author: Språkbanken Text
Author-email: Språkbanken Text <sb-info@svenska.gu.se>
Classifier: Development Status :: 3 - Alpha
Classifier: Intended Audience :: Developers
Classifier: License :: OSI Approved :: MIT License
Classifier: Operating System :: Unix
Classifier: Operating System :: POSIX
Classifier: Programming Language :: Python :: 3.11
Classifier: Programming Language :: Python :: 3.12
Classifier: Programming Language :: Python :: 3.13
Classifier: Programming Language :: Python :: Implementation :: CPython
Classifier: Topic :: Utilities
Requires-Dist: sparv>=5.3.1
Requires-Dist: torch>=2.8.0
Requires-Dist: transformers>=4.56.1
Requires-Python: >=3.11
Project-URL: Changelog, https://github.com/spraakbanken/sparv-sbx-whisper-import/blob/main/CHANGELOG.md
Project-URL: Homepage, https://spraakbanken.gu.se
Project-URL: Issues, https://github.com/spraakbanken/sparv-sbx-whisper-import/issues
Project-URL: Repository, https://github.com/spraakbanken/sparv-sbx-whisper-import
